rdl.py
rdl-1.2.0.dist-info/DESCRIPTION.rst
rdl-1.2.0.dist-info/METADATA
rdl-1.2.0.dist-info/RECORD
rdl-1.2.0.dist-info/WHEEL
rdl-1.2.0.dist-info/entry_points.txt
rdl-1.2.0.dist-info/metadata.json
rdl-1.2.0.dist-info/top_level.txt
