Metadata-Version: 2.0
Name: rdl
Version: 1.2.0
Summary: Redis dump & load tool.
Home-page: https://github.com/reorx/rdl
Author: reorx
Author-email: UNKNOWN
License: License :: OSI Approved :: MIT License
Platform: UNKNOWN
Requires-Dist: redis (>=2.9)
